odoo/addons/ssi_payment_order_cheque_voucher/README.rst
odoo/addons/ssi_payment_order_cheque_voucher/__init__.py
odoo/addons/ssi_payment_order_cheque_voucher/__manifest__.py
odoo/addons/ssi_payment_order_cheque_voucher/models/__init__.py
odoo/addons/ssi_payment_order_cheque_voucher/models/cheque_payment.py
odoo/addons/ssi_payment_order_cheque_voucher/models/payment_order.py
odoo/addons/ssi_payment_order_cheque_voucher/models/payment_order_type.py
odoo/addons/ssi_payment_order_cheque_voucher/models/payment_request.py
odoo/addons/ssi_payment_order_cheque_voucher/static/description/icon.png
odoo/addons/ssi_payment_order_cheque_voucher/views/cheque_payment_views.xml
odoo/addons/ssi_payment_order_cheque_voucher/views/payment_order_views.xml
odoo14_addon_ssi_payment_order_cheque_voucher-14.0.1.1.1.dist-info/METADATA
odoo14_addon_ssi_payment_order_cheque_voucher-14.0.1.1.1.dist-info/WHEEL
odoo14_addon_ssi_payment_order_cheque_voucher-14.0.1.1.1.dist-info/top_level.txt
odoo14_addon_ssi_payment_order_cheque_voucher-14.0.1.1.1.dist-info/RECORD
