Metadata-Version: 2.1
Name: odoo14-addon-ssi-payment-order-cheque-voucher
Version: 14.0.1.1.1
Summary: Payment Order + Cheque Voucher
Home-page: https://simetri-sinergi.id
Author: PT. Simetri Sinergi Indonesia, OpenSynergy Indonesia
License: AGPL-3
Platform: UNKNOWN
Classifier: Programming Language :: Python
Classifier: Framework :: Odoo
Classifier: Framework :: Odoo :: 14.0
Classifier: License :: OSI Approved :: GNU Affero General Public License v3
Requires-Python: >=3.6
Requires-Dist: odoo14-addon-ssi-payment-order
Requires-Dist: odoo14-addon-ssi-voucher-cheque
Requires-Dist: odoo (<14.1dev,>=14.0a)
